README.rst
setup.py
json_awk/__init__.py
json_awk/runner.py
json_awk.egg-info/PKG-INFO
json_awk.egg-info/SOURCES.txt
json_awk.egg-info/dependency_links.txt
json_awk.egg-info/top_level.txt