Metadata-Version: 1.1
Name: json-awk
Version: 1.0.1.dev1
Summary: A simple JSON parser and printer
Home-page: https://github.com/pgmillon/json-awk
Author: Pierre-Gildas MILLON
Author-email: pg.millon@gmail.com
License: GPLv2
Keywords: json awk
Platform: UNKNOWN
Classifier: Development Status :: 3 - Alpha
Classifier: Intended Audience :: Developers
Classifier: Topic :: Utilities
Classifier: License :: OSI Approved :: GNU General Public License v2 (GPLv2)
Classifier: Programming Language :: Python :: 2.7
